streamlit_gsheets/__init__.py
streamlit_gsheets/gsheets_connection.py
st_gsheets_connection-0.0.4.dist-info/METADATA
st_gsheets_connection-0.0.4.dist-info/WHEEL
st_gsheets_connection-0.0.4.dist-info/top_level.txt
st_gsheets_connection-0.0.4.dist-info/RECORD
